open3d_ros_helper/__init__.py
open3d_ros_helper/open3d_ros_helper.py
open3d_ros_helper-0.2.0.3.dist-info/LICENSE
open3d_ros_helper-0.2.0.3.dist-info/METADATA
open3d_ros_helper-0.2.0.3.dist-info/WHEEL
open3d_ros_helper-0.2.0.3.dist-info/top_level.txt
open3d_ros_helper-0.2.0.3.dist-info/RECORD
