Metadata-Version: 2.1
Name: open3d-ros-helper
Version: 0.2.0.3
Summary: A helper tool for jointly using open3d and ROS
Home-page: https://github.com/SeungBack/open3d-ros-helper
Author: Seunghyeok Back
Author-email: shback@gist.ac.kr
License: UNKNOWN
Platform: UNKNOWN
Classifier: Programming Language :: Python :: 2.7
Classifier: License :: OSI Approved :: MIT License
Classifier: Operating System :: OS Independent
